flightmatrix/__init__.py
flightmatrix/bridge.py
flightmatrix/server.py
flightmatrix/utilities.py
flightmatrixbridge-1.7.0.dist-info/LICENSE.rst
flightmatrixbridge-1.7.0.dist-info/METADATA
flightmatrixbridge-1.7.0.dist-info/WHEEL
flightmatrixbridge-1.7.0.dist-info/top_level.txt
flightmatrixbridge-1.7.0.dist-info/RECORD
