Metadata-Version: 2.1
Name: flightmatrixbridge
Version: 1.7.0
Summary: FlightMatrixBridge is a Python library that facilitates seamless inter-process communication between the Flight Matrix software using shared memory. It handles frames, timestamps, and movement commands for efficient data sharing in robotics applications.
Home-page: https://github.com/Kawai-Senpai/Py-FlightMatrix-Bridge
Download-URL: https://github.com/Kawai-Senpai/Py-FlightMatrix-Bridge
Author: Ranit Bhowmick
Author-email: bhowmickranitking@duck.com
License: MIT License with attribution requirement
Keywords: Robotics,Inter-process communication,Shared memory,Data management
License-File: LICENSE.rst
Requires-Dist: numpy
Requires-Dist: ultraprint
Requires-Dist: opencv-python
